source/__init__.py
source/scam.py
source/backend/__init__.py
source/backend/analyzer.py
source/backend/common_fingerprints.py
source/backend/file_to_fingerprint.py
source/backend/fingerprint.py
source/backend/interface.py
source/backend/winnowing.py
source/frontend/SCAM.png
source/frontend/__init__.py
source/frontend/gui/doc_obj.ui
source/frontend/gui/help_manual.ui
source/frontend/gui/match_obj.ui
source/frontend/gui/scam_gui.ui
source/frontend/pages/__init__.py
source/frontend/pages/compare_page.py
source/frontend/pages/results_page.py
source/frontend/pages/search_page.py
source/frontend/util/__init__.py
source/frontend/util/document.py
scam-0.3.12.dist-info/METADATA
scam-0.3.12.dist-info/WHEEL
scam-0.3.12.dist-info/entry_points.txt
scam-0.3.12.dist-info/top_level.txt
scam-0.3.12.dist-info/RECORD
