Metadata-Version: 2.1
Name: scam
Version: 0.3.12
Summary: Source Code Analyzing Maching is an application for the analysis of similarities between source code files. Currently with Python, Java, C, and C++ file checking capabilities.
Home-page: https://github.com/SourceCodeAnalyzingMachine/SCAM_Public
Author: Codalyzers
Author-email: djoni.austin@gmail.com
License: UNKNOWN
Platform: UNKNOWN
Classifier: Programming Language :: Python :: 3
Classifier: License :: OSI Approved :: MIT License
Classifier: Operating System :: OS Independent
Requires-Python: >=3.6
Requires-Dist: javalang
Requires-Dist: PySide2
Requires-Dist: matplotlib
Requires-Dist: networkx
Requires-Dist: clang
Requires-Dist: pycparser
Requires-Dist: grave
